unofficial_shipengine/__init__.py
unofficial_shipengine/core/__init__.py
unofficial_shipengine/core/batches/__init__.py
unofficial_shipengine/core/batches/enums.py
unofficial_shipengine/core/batches/models.py
unofficial_shipengine/core/batches/services.py
unofficial_shipengine/core/carriers/__init__.py
unofficial_shipengine/core/carriers/models.py
unofficial_shipengine/core/carriers/services.py
unofficial_shipengine/core/common/__init__.py
unofficial_shipengine/core/common/enums.py
unofficial_shipengine/core/common/models.py
unofficial_shipengine/core/common/services.py
unofficial_shipengine/core/labels/__init__.py
unofficial_shipengine/core/labels/enums.py
unofficial_shipengine/core/labels/models.py
unofficial_shipengine/core/labels/services.py
unofficial_shipengine/core/shipments/__init__.py
unofficial_shipengine/core/shipments/enums.py
unofficial_shipengine/core/shipments/models.py
unofficial_shipengine/core/shipments/services.py
unofficial_shipengine/core/tracking/__init__.py
unofficial_shipengine/core/tracking/enums.py
unofficial_shipengine/core/tracking/models.py
unofficial_shipengine/core/tracking/services.py
unofficial_shipengine/core/warehouses/__init__.py
unofficial_shipengine/core/warehouses/models.py
unofficial_shipengine/core/warehouses/services.py
unofficial_shipengine/exceptions.py
unofficial_shipengine/py.typed
unofficial_shipengine/unofficial_shipengine.py
unofficial_shipengine/unofficial_shipengine_config.py
unofficial_shipengine/utils/__init__.py
unofficial_shipengine/utils/serialize.py
unofficial_shipengine-0.1.0.dist-info/LICENSE
unofficial_shipengine-0.1.0.dist-info/METADATA
unofficial_shipengine-0.1.0.dist-info/WHEEL
unofficial_shipengine-0.1.0.dist-info/RECORD
