Metadata-Version: 2.1
Name: unofficial-shipengine
Version: 0.1.0
Summary: 
Author: Richard Smith
Author-email: programming.smithr@gmail.com
Requires-Python: >=3.12,<4.0
Classifier: Programming Language :: Python :: 3
Classifier: Programming Language :: Python :: 3.12
Requires-Dist: attrs (>=23.2.0,<24.0.0)
Requires-Dist: requests (>=2.31.0,<3.0.0)
